tabs_type/__init__.py
tabs_type/cell.py
tabs_type/version.py
tabs_type-0.1.0.dist-info/WHEEL
tabs_type-0.1.0.dist-info/METADATA
tabs_type-0.1.0.dist-info/RECORD
