Metadata-Version: 2.1
Name: tabs-type
Version: 0.1.0
Summary: Some general useful types for tabs
License: MIT
Author-email: Alexis Rosuel <rosuelalexis1@gmail.com>
Requires-Python: >=3.11
Requires-Dist: tabs-settings>=0.1.0
Requires-Dist: xarray>=2023.2.0
